pyem410x/__init__.py
pyem410x/core.py
pyem410x-1.0.0.dist-info/DESCRIPTION.rst
pyem410x-1.0.0.dist-info/METADATA
pyem410x-1.0.0.dist-info/RECORD
pyem410x-1.0.0.dist-info/WHEEL
pyem410x-1.0.0.dist-info/metadata.json
pyem410x-1.0.0.dist-info/top_level.txt
