Metadata-Version: 2.0
Name: pyem410x
Version: 1.0.0
Summary: A python module for encode & decode Em410x.
Home-page: https://github.com/yrjyrj123/pyem410x
Author: yrjyrj123
Author-email: yrjyrjwp7@hotmail.com
License: MIT
Keywords: em410x t5577 t55xx rfid id card
Platform: UNKNOWN
Classifier: Development Status :: 4 - Beta
Classifier: License :: OSI Approved :: MIT License
Classifier: Programming Language :: Python
Classifier: Programming Language :: Python :: 2
Classifier: Programming Language :: Python :: 2.7
Classifier: Programming Language :: Python :: 3
Classifier: Programming Language :: Python :: 3.2
Classifier: Programming Language :: Python :: 3.3
Classifier: Programming Language :: Python :: 3.4
Classifier: Programming Language :: Python :: 3.5
Requires-Dist: bitstring
